setup.py
newpipv1/__init__.py
newpipv1.egg-info/PKG-INFO
newpipv1.egg-info/SOURCES.txt
newpipv1.egg-info/dependency_links.txt
newpipv1.egg-info/top_level.txt