Metadata-Version: 2.1
Name: newpipv1
Version: 0.1.0
Summary: package for pentesting
Author: anand
